sproclib/__init__.py
sproclib/analysis/__init__.py
sproclib/analysis/model_identification.py
sproclib/analysis/system_analysis.py
sproclib/analysis/transfer_function.py
sproclib/controller/__init__.py
sproclib/controller/index.rst
sproclib/controller/base/TuningRule.py
sproclib/controller/base/__init__.py
sproclib/controller/model_based/IMCController.py
sproclib/controller/model_based/IMCController.rst
sproclib/controller/model_based/IMCController_documentation.md
sproclib/controller/model_based/IMCController_simple_example.py
sproclib/controller/model_based/IMCController_test.py
sproclib/controller/model_based/__init__.py
sproclib/controller/model_based/create_imc_plots.py
sproclib/controller/pid/PIDController.py
sproclib/controller/pid/PIDController.rst
sproclib/controller/pid/PIDController_documentation.md
sproclib/controller/pid/PIDController_example.py
sproclib/controller/pid/PIDController_simple_example.py
sproclib/controller/pid/PIDController_test.py
sproclib/controller/pid/__init__.py
sproclib/controller/pid/create_pid_plots.py
sproclib/controller/state_space/StateSpaceController.py
sproclib/controller/state_space/StateSpaceController.rst
sproclib/controller/state_space/StateSpaceController_documentation.md
sproclib/controller/state_space/StateSpaceController_example.py
sproclib/controller/state_space/StateSpaceController_simple_example.py
sproclib/controller/state_space/StateSpaceController_test.py
sproclib/controller/state_space/__init__.py
sproclib/controller/state_space/create_statespace_plots.py
sproclib/controller/tuning/AMIGOTuning.py
sproclib/controller/tuning/AMIGOTuning_documentation.md
sproclib/controller/tuning/AMIGOTuning_simple_example.py
sproclib/controller/tuning/AMIGOTuning_test.py
sproclib/controller/tuning/RelayTuning.py
sproclib/controller/tuning/RelayTuning_documentation.md
sproclib/controller/tuning/RelayTuning_simple_example.py
sproclib/controller/tuning/RelayTuning_test.py
sproclib/controller/tuning/ZieglerNicholsTuning.py
sproclib-3.0.1.dist-info/licenses/LICENSE
sproclib-3.0.1.dist-info/METADATA
sproclib-3.0.1.dist-info/WHEEL
sproclib-3.0.1.dist-info/top_level.txt
sproclib-3.0.1.dist-info/RECORD
