Metadata-Version: 2.4
Name: sproclib
Version: 3.0.1
Summary: Standard Process Control Library for chemical process control - Semantic API for chemical plant design using familiar ML patterns
Home-page: https://github.com/gressling/sproclib
Author: Thorsten Gressling
Author-email: Thorsten Gressling <gressling@paramus.ai>
License: MIT
Project-URL: Homepage, https://github.com/gressling/sproclib
Project-URL: Repository, https://github.com/gressling/sproclib
Project-URL: Issues, https://github.com/gressling/sproclib/issues
Project-URL: Documentation, https://sproclib.readthedocs.io/en/latest/
Keywords: process control,chemical engineering,PID,simulation,optimization,semantic API,machine learning
Classifier: Development Status :: 5 - Production/Stable
Classifier: Intended Audience :: Science/Research
Classifier: Intended Audience :: Manufacturing
Classifier: License :: OSI Approved :: MIT License
Classifier: Operating System :: OS Independent
Classifier: Programming Language :: Python :: 3
Classifier: Programming Language :: Python :: 3.8
Classifier: Programming Language :: Python :: 3.9
Classifier: Programming Language :: Python :: 3.10
Classifier: Programming Language :: Python :: 3.11
Classifier: Programming Language :: Python :: 3.12
Classifier: Topic :: Scientific/Engineering
Classifier: Topic :: Scientific/Engineering :: Chemistry
Classifier: Topic :: Scientific/Engineering :: Artificial Intelligence
Requires-Python: >=3.8
License-File: LICENSE
Requires-Dist: numpy>=1.20.0
Requires-Dist: scipy>=1.7.0
Requires-Dist: matplotlib>=3.3.0
Provides-Extra: dev
Requires-Dist: pytest>=6.0; extra == "dev"
Requires-Dist: black; extra == "dev"
Requires-Dist: flake8; extra == "dev"
Requires-Dist: mypy; extra == "dev"
Provides-Extra: optimization
Requires-Dist: cvxpy>=1.1.0; extra == "optimization"
Requires-Dist: gekko>=1.0.0; extra == "optimization"
Dynamic: author
Dynamic: home-page
Dynamic: license-file
Dynamic: requires-python
